shubhamsareliya.py
shubhamsareliya-0.1.0.dist-info/METADATA
shubhamsareliya-0.1.0.dist-info/WHEEL
shubhamsareliya-0.1.0.dist-info/RECORD
