Metadata-Version: 2.1
Name: shubhamsareliya
Version: 0.1.0
Summary: This is a Testing/Training Project
Author: Shubham Sareliya
Author-email: shubham.sareliya@crestdatasys.com
Requires-Python: >=3.10,<4.0
Classifier: Programming Language :: Python :: 3
Classifier: Programming Language :: Python :: 3.10
Classifier: Programming Language :: Python :: 3.11
Classifier: Programming Language :: Python :: 3.12
Requires-Dist: pytest (>=7.4.3,<8.0.0)
